{
  "id": "fvtt-shared-window",
  "name": "fvtt-shared-window",
  "title": "Shared Window", 
  "description": "A shared window for both GM and players",
  "version": "1.0.0",
  "compatibility": {
    "minimum": "10",
    "verified": "11"
  },
  "authors": [
    {
      "name": "murderer0107",
      "url": "https://github.com/murderer0107/fvtt-shared-window"
    }
  ],
  "esmodules": ["scripts/main.js"],
  "styles": ["styles/main.css"],
  "socket": true,
  "manifest": "https://murderer0107.github.io/fvtt-shared-window/module.json",
  "download": "https://murderer0107.github.io/fvtt-shared-window/module.zip",
  "url": "https://github.com/murderer0107/fvtt-shared-window"
}